nfl_veripy/__init__.py
nfl_veripy/example.py
nfl_veripy/online_verification.py
nfl_veripy/_static/datasets/README.md
nfl_veripy/_static/datasets/double_integrator/us.pkl
nfl_veripy/_static/datasets/double_integrator/xs.pkl
nfl_veripy/_static/datasets/double_integrator2/us.pkl
nfl_veripy/_static/datasets/double_integrator2/xs.pkl
nfl_veripy/_static/datasets/duffing/us.csv
nfl_veripy/_static/datasets/duffing/xs.csv
nfl_veripy/_static/datasets/iss/iss.mat
nfl_veripy/_static/datasets/iss/us.csv
nfl_veripy/_static/datasets/iss/xs.csv
nfl_veripy/_static/datasets/quadrotor/us.pkl
nfl_veripy/_static/datasets/quadrotor/xs.pkl
nfl_veripy/_static/example_configs/acc23_/testing
nfl_veripy/_static/example_configs/access21/backreach.yaml
nfl_veripy/_static/example_configs/access21/duffing.yaml
nfl_veripy/_static/example_configs/access21/greedy_sim_guided.yaml
nfl_veripy/_static/example_configs/access21/iss.yaml
nfl_veripy/_static/example_configs/access21/sim_guided.yaml
nfl_veripy/_static/example_configs/cdc22/fig3a.yaml
nfl_veripy/_static/example_configs/cdc22/fig4a.yaml
nfl_veripy/_static/example_configs/cdc22/fig4b.yaml
nfl_veripy/_static/example_configs/cdc22/fig4c.yaml
nfl_veripy/_static/example_configs/cdc22/fig5.yaml
nfl_veripy/_static/example_configs/icra21/fig3_reach_lp.yaml
nfl_veripy/_static/example_configs/icra21/fig3_reach_lp_partition.yaml
nfl_veripy/_static/example_configs/icra21/fig3_reach_sdp.yaml
nfl_veripy/_static/example_configs/icra21/fig3_reach_sdp_partition.yaml
nfl_veripy/_static/example_configs/icra21/fig4b.yaml
nfl_veripy/_static/example_configs/icra21/fig5a.yaml
nfl_veripy/_static/example_configs/icra21/fig5b.yaml
nfl_veripy/_static/example_configs/jax/jax_fwd_double_integrator.yaml
nfl_veripy/_static/example_configs/jax/jax_fwd_double_integrator_jit.yaml
nfl_veripy/_static/example_configs/jax/jax_fwd_quadrotor.yaml
nfl_veripy/_static/example_configs/lcss23/fig2_breachlp.yaml
nfl_veripy/_static/example_configs/lcss23/fig2_breachlp_iterate.yaml
nfl_veripy-0.0.2.dist-info/METADATA
nfl_veripy-0.0.2.dist-info/WHEEL
nfl_veripy-0.0.2.dist-info/licenses/LICENSE
nfl_veripy-0.0.2.dist-info/RECORD
