Metadata-Version: 2.1
Name: nfl_veripy
Version: 0.0.2
Summary: Formal verification of neural feedback loops (NFLs)
Project-URL: repository, https://github.com/neu-autonomy/nfl_veripy.git
Author-email: Michael Everett <m.everett@northeastern.edu>, Nicholas Rober <nrober@mit.edu>
License: MIT License
License-File: LICENSE
Classifier: License :: OSI Approved :: MIT License
Classifier: Operating System :: OS Independent
Classifier: Programming Language :: Python :: 3
Requires-Python: >=3.7
Requires-Dist: alphashape
Requires-Dist: auto-lirpa
Requires-Dist: colour
Requires-Dist: crown-ibp
Requires-Dist: imageio
Requires-Dist: jax
Requires-Dist: jax-verify
Requires-Dist: matplotlib
Requires-Dist: mypy
Requires-Dist: pandas
Requires-Dist: parameterized
Requires-Dist: pyclipper
Requires-Dist: pygifsicle
Requires-Dist: pylint
Requires-Dist: pypoman
Requires-Dist: scikit-learn
Requires-Dist: scipy
Requires-Dist: tabulate
Requires-Dist: torch
Requires-Dist: tqdm
